clearml_session/__init__.py
clearml_session/__main__.py
clearml_session/interactive_session_task.py
clearml_session/single_thread_proxy.py
clearml_session/tcp_proxy.py
clearml_session/version.py
clearml_session-0.17.0.dist-info/LICENSE
clearml_session-0.17.0.dist-info/METADATA
clearml_session-0.17.0.dist-info/WHEEL
clearml_session-0.17.0.dist-info/entry_points.txt
clearml_session-0.17.0.dist-info/top_level.txt
clearml_session-0.17.0.dist-info/RECORD
