Metadata-Version: 2.1
Name: clearml-session
Version: 0.17.0
Summary: clearml-session - CLI for launching JupyterLab / VSCode on a remote machine
Home-page: https://github.com/allegroai/clearml-session
Author: Allegroai
Author-email: clearml@allegro.ai
License: Apache License 2.0
Keywords: clearml mlops devops trains development machine deep learning version control machine-learning machinelearning deeplearning deep-learning experiment-manager jupyter vscode
Platform: UNKNOWN
Classifier: Development Status :: 5 - Production/Stable
Classifier: Intended Audience :: Developers
Classifier: Intended Audience :: Science/Research
Classifier: Operating System :: POSIX :: Linux
Classifier: Operating System :: MacOS :: MacOS X
Classifier: Operating System :: Microsoft
Classifier: Topic :: Scientific/Engineering :: Artificial Intelligence
Classifier: Topic :: Software Development
Classifier: Topic :: Software Development :: Version Control
Classifier: Topic :: System :: Logging
Classifier: Topic :: System :: Monitoring
Classifier: Programming Language :: Python :: 3.5
Classifier: Programming Language :: Python :: 3.6
Classifier: Programming Language :: Python :: 3.7
Classifier: Programming Language :: Python :: 3.8
Classifier: Programming Language :: Python :: 3.9
Classifier: Programming Language :: Python :: 3.10
Classifier: Programming Language :: Python :: 3.11
Classifier: Programming Language :: Python :: 3.12
Classifier: License :: OSI Approved :: Apache Software License
Requires-Dist: clearml (>=1.9)
Requires-Dist: psutil
Requires-Dist: pexpect ; sys_platform != "win32"
Requires-Dist: wexpect-venv ; sys_platform == "win32"
